testing_tools/__init__.py
testing_tools/common_path.py
testing_tools/error.py
testing_tools/notebook.py
testing_tools-1.0.3.dist-info/METADATA
testing_tools-1.0.3.dist-info/WHEEL
testing_tools-1.0.3.dist-info/top_level.txt
testing_tools-1.0.3.dist-info/RECORD
